odoo8_addon_crm_lead_website-8.0.1.0.0.99.dev25-py3.8-nspkg.pth
odoo_addons/crm_lead_website/README.rst
odoo_addons/crm_lead_website/__init__.py
odoo_addons/crm_lead_website/__openerp__.py
odoo_addons/crm_lead_website/models.py
odoo_addons/crm_lead_website/i18n/ar.po
odoo_addons/crm_lead_website/i18n/bg.po
odoo_addons/crm_lead_website/i18n/bs.po
odoo_addons/crm_lead_website/i18n/ca.po
odoo_addons/crm_lead_website/i18n/crm_lead_website.pot
odoo_addons/crm_lead_website/i18n/cs.po
odoo_addons/crm_lead_website/i18n/da.po
odoo_addons/crm_lead_website/i18n/de.po
odoo_addons/crm_lead_website/i18n/el_GR.po
odoo_addons/crm_lead_website/i18n/en_GB.po
odoo_addons/crm_lead_website/i18n/es.po
odoo_addons/crm_lead_website/i18n/es_AR.po
odoo_addons/crm_lead_website/i18n/es_CL.po
odoo_addons/crm_lead_website/i18n/es_CO.po
odoo_addons/crm_lead_website/i18n/es_CR.po
odoo_addons/crm_lead_website/i18n/es_DO.po
odoo_addons/crm_lead_website/i18n/es_EC.po
odoo_addons/crm_lead_website/i18n/es_MX.po
odoo_addons/crm_lead_website/i18n/es_PE.po
odoo_addons/crm_lead_website/i18n/et.po
odoo_addons/crm_lead_website/i18n/eu.po
odoo_addons/crm_lead_website/i18n/fa.po
odoo_addons/crm_lead_website/i18n/fi.po
odoo_addons/crm_lead_website/i18n/fr.po
odoo_addons/crm_lead_website/i18n/he.po
odoo_addons/crm_lead_website/i18n/hr.po
odoo_addons/crm_lead_website/i18n/hr_HR.po
odoo_addons/crm_lead_website/i18n/hu.po
odoo_addons/crm_lead_website/i18n/id.po
odoo_addons/crm_lead_website/i18n/it.po
odoo_addons/crm_lead_website/i18n/ja.po
odoo_addons/crm_lead_website/i18n/ko.po
odoo_addons/crm_lead_website/i18n/lt.po
odoo_addons/crm_lead_website/i18n/lv.po
odoo_addons/crm_lead_website/i18n/mk.po
odoo_addons/crm_lead_website/i18n/mn.po
odoo_addons/crm_lead_website/i18n/nb.po
odoo_addons/crm_lead_website/i18n/pl.po
odoo_addons/crm_lead_website/i18n/pt_BR.po
odoo_addons/crm_lead_website/i18n/ru.po
odoo_addons/crm_lead_website/i18n/sk.po
odoo_addons/crm_lead_website/i18n/sl.po
odoo_addons/crm_lead_website/i18n/sr.po
odoo8_addon_crm_lead_website-8.0.1.0.0.99.dev25.dist-info/METADATA
odoo8_addon_crm_lead_website-8.0.1.0.0.99.dev25.dist-info/WHEEL
odoo8_addon_crm_lead_website-8.0.1.0.0.99.dev25.dist-info/namespace_packages.txt
odoo8_addon_crm_lead_website-8.0.1.0.0.99.dev25.dist-info/top_level.txt
odoo8_addon_crm_lead_website-8.0.1.0.0.99.dev25.dist-info/RECORD
